urlrequest/__init__.py
urlrequest/urlrequest.py
urlrequest-1.0.3.dist-info/LICENSE
urlrequest-1.0.3.dist-info/METADATA
urlrequest-1.0.3.dist-info/WHEEL
urlrequest-1.0.3.dist-info/top_level.txt
urlrequest-1.0.3.dist-info/RECORD
