Metadata-Version: 2.1
Name: urlrequest
Version: 1.0.3
Summary: Wrapper for urllib.request.urlopen
Home-page: https://github.com/Sumiza/urlrequest/
Author: Sumiza
Author-email: sumiza@gmail.com
Project-URL: Bug Tracker, https://github.com/Sumiza/urlrequest/issues
Classifier: Programming Language :: Python :: 3.9
Classifier: Programming Language :: Python :: 3.10
Classifier: License :: OSI Approved :: MIT License
Classifier: Operating System :: OS Independent
Requires-Python: >=3.9
License-File: LICENSE
